tautulli/API_VERSIONS.json
tautulli/PYTHON_VERSIONS.json
tautulli/__init__.py
tautulli/_info.py
tautulli/api/__init__.py
tautulli/api/json_api.py
tautulli/api/object_api.py
tautulli/exceptions/__init__.py
tautulli/exceptions/api_exception.py
tautulli/exceptions/base_exception.py
tautulli/exceptions/http_exception.py
tautulli/exceptions/json_exception.py
tautulli/exceptions/plex_exception.py
tautulli/internal/__init__.py
tautulli/internal/decorators.py
tautulli/internal/static.py
tautulli/internal/utils.py
tautulli/models/__init__.py
tautulli/models/_base.py
tautulli/models/activity.py
tautulli/models/children_metadata.py
tautulli/models/collections_table.py
tautulli/models/date_formats.py
tautulli/models/docs.py
tautulli/models/export_fields.py
tautulli/models/exports_table.py
tautulli/models/geo_ip_lookup.py
tautulli/models/get_plays_or_stream_types_by.py
tautulli/models/history.py
tautulli/models/home_stats.py
tautulli/models/item_user_stats.py
tautulli/models/item_watch_time_stats.py
tautulli/models/libraries.py
tautulli/models/libraries_table.py
tautulli/models/library.py
tautulli/models/library_media_info.py
tautulli/models/library_names.py
tautulli/models/library_user_stats.py
tautulli/models/library_watch_time_stats.py
tautulli/models/logs.py
tautulli/models/metadata.py
tautulli/models/new_rating_keys.py
tautulli/models/newsletter.py
tautulli/models/newsletter_config.py
tautulli/models/newsletter_log.py
tautulli/models/newsletter_notification.py
tautulli/models/notification.py
tautulli/models/notification_log.py
tautulli/models/notifier_config.py
tautulli/models/notifier_parameters.py
tautulli/models/notifiers.py
tautulli/models/old_rating_keys.py
tautulli/models/parser.py
tautulli/models/playlists_table.py
tautulli/models/plex_log.py
tautulli/models/pms_update.py
tautulli/models/recently_added.py
tautulli/models/registered_device.py
tautulli/models/search_results.py
tautulli/models/server_id.py
tautulli/models/server_identity.py
tautulli-4.6.7.2142.dist-info/LICENSE
tautulli-4.6.7.2142.dist-info/METADATA
tautulli-4.6.7.2142.dist-info/WHEEL
tautulli-4.6.7.2142.dist-info/top_level.txt
tautulli-4.6.7.2142.dist-info/RECORD
