Metadata-Version: 2.1
Name: tautulli
Version: 4.6.7.2142
Summary: A complete Python client for Tautulli's API
Home-page: https://github.com/nwithan8/pytulli
Download-URL: https://github.com/nwithan8/pytulli/archive/refs/tags/4.6.7.2142.tar.gz
Author: Nate Harris
Author-email: n8gr8gbln@gmail.com
License: GNU General Public License v3 (GPLv3)
Keywords: Tautulli,API,client,Plex,PMS,Plex Media Server,media,server,JSON
Classifier: License :: OSI Approved :: GNU General Public License v3 (GPLv3)
Classifier: Development Status :: 4 - Beta
Classifier: Intended Audience :: Developers
Classifier: Topic :: Software Development :: Build Tools
Classifier: Topic :: Multimedia :: Video
Classifier: Topic :: Multimedia
Classifier: Topic :: Internet :: WWW/HTTP
Classifier: Operating System :: OS Independent
Classifier: Programming Language :: Python :: 3
Classifier: Programming Language :: Python :: 3.8
Classifier: Programming Language :: Python :: 3.9
Classifier: Programming Language :: Python :: 3.10
Classifier: Programming Language :: Python :: 3.11
Classifier: Programming Language :: Python :: 3.12
Classifier: Programming Language :: Python :: 3.13
Requires-Python: >=3.8, <4
License-File: LICENSE
Requires-Dist: objectrest ==2.0.*
Requires-Dist: pydantic >=2.10.0
Requires-Dist: pytz ==2024.*
Requires-Dist: python-dotenv ==1.0.*
Requires-Dist: packaging ==24.*
Requires-Dist: typing-extensions
Requires-Dist: PlexAPI ==4.15.*,>=4.15.14
Provides-Extra: dev
Requires-Dist: black ; extra == 'dev'
Requires-Dist: flake8 ; extra == 'dev'
Requires-Dist: isort ; extra == 'dev'
Requires-Dist: pytest-cov ==3.* ; extra == 'dev'
Requires-Dist: pytest-vcr ==1.* ; extra == 'dev'
Requires-Dist: pytest ==7.* ; extra == 'dev'
Requires-Dist: types-requests ; extra == 'dev'
Requires-Dist: types-urllib3 ; extra == 'dev'
Requires-Dist: vcrpy ==4.* ; extra == 'dev'
Requires-Dist: pre-commit ; extra == 'dev'
Requires-Dist: sphinx ; extra == 'dev'
Requires-Dist: sphinx-rtd-theme ; extra == 'dev'
Requires-Dist: sphinx-jsonschema ; extra == 'dev'
Requires-Dist: sphinx-pydantic ; extra == 'dev'
Requires-Dist: sphinx-autodoc-typehints ; extra == 'dev'
